<mets:mets xmlns:mets="http://www.loc.gov/METS/" xmlns:mods="http://www.loc.gov/mods/v3" xmlns:xlink="http://www.w3.org/1999/xlink">
    <mets:dmdSec ID="DMD_rub-journals_481">
        <mets:mdWrap MIMETYPE="text/xml" MDTYPE="MODS">
            <mets:xmlData>
                <mods xmlns="http://www.loc.gov/mods/v3" version="3.7" xmlns:vl="http://visuallibrary.net/vl">
                    <titleInfo lang="eng">
                        <title>Announcements and Calls for Articles</title>
                    </titleInfo>
                    <name type="personal">
                        <displayForm>Authors, Various</displayForm>
                        <namePart type="family">Authors</namePart>
                        <namePart type="given">Various</namePart>
                        <role>
                            <roleTerm type="code" authority="marcrelator">ctb</roleTerm>
                        </role>
                    </name>
                    <typeOfResource>text</typeOfResource>
                    <genre authority="dini">article</genre>
                    <originInfo>
                        <dateIssued encoding="w3cdtf" keyDate="yes">2016-06-01</dateIssued>
                    </originInfo>
                    <language>
                        <languageTerm type="code" authority="iso639-2b">eng</languageTerm>
                    </language>
                    <physicalDescription>
                        <extent unit="page">2</extent>
                    </physicalDescription>
                    <abstract lang="eng">On the Fringes of the Revolution: Marginalization and Emancipation in the  Global Cycle of Revolutions 1917-1923. Call for papers for a special issue of “Arbeit – Bewegung – Geschichte” (Labour – Movement – History).</abstract>
                    <subject lang="ger">
                    </subject>
                    <subject lang="eng">
                    </subject>
                    <recordInfo>
                        <recordIdentifier>rub-journals_481</recordIdentifier>
                    </recordInfo>
                    <extension>
                        <vl:doctype>oaArticle</vl:doctype>
                    </extension>
                </mods>
            </mets:xmlData>
        </mets:mdWrap>
    </mets:dmdSec>
    <mets:fileSec>
        <mets:fileGrp USE="pdf upload">
            <mets:file MIMETYPE="application/pdf" ID="FILE0_rub-journals_481">
                <mets:FLocat xlink:href="https://incs.ub.rub.de/index.php/INCS/article/download/481/433" LOCTYPE="URL"/>
            </mets:file>
        </mets:fileGrp>
    </mets:fileSec>
    <mets:structMap TYPE="LOGICAL">
        <mets:div TYPE="document" ID="rub-journals_481" DMDID="DMD_rub-journals_481">
            <mets:fptr FILEID="FILE0_rub-journals_481"/>
        </mets:div>
    </mets:structMap>
</mets:mets>
