<mets:mets xmlns:mets="http://www.loc.gov/METS/" xmlns:mods="http://www.loc.gov/mods/v3" xmlns:xlink="http://www.w3.org/1999/xlink">
    <mets:dmdSec ID="DMD_rub-journals_638">
        <mets:mdWrap MIMETYPE="text/xml" MDTYPE="MODS">
            <mets:xmlData>
                <mods xmlns="http://www.loc.gov/mods/v3" version="3.7" xmlns:vl="http://visuallibrary.net/vl">
                    <titleInfo lang="eng">
                        <title>Human-readable Proof of the Related-Key Security of AES-128</title>
                    </titleInfo>
                    <name type="personal">
                        <displayForm>Khoo, Khoongming</displayForm>
                        <namePart type="family">Khoo</namePart>
                        <namePart type="given">Khoongming</namePart>
                        <role>
                            <roleTerm type="code" authority="marcrelator">ctb</roleTerm>
                        </role>
                    </name>
                    <name type="personal">
                        <displayForm>Lee, Eugene</displayForm>
                        <namePart type="family">Lee</namePart>
                        <namePart type="given">Eugene</namePart>
                        <role>
                            <roleTerm type="code" authority="marcrelator">ctb</roleTerm>
                        </role>
                    </name>
                    <name type="personal">
                        <displayForm>Peyrin, Thomas</displayForm>
                        <namePart type="family">Peyrin</namePart>
                        <namePart type="given">Thomas</namePart>
                        <role>
                            <roleTerm type="code" authority="marcrelator">ctb</roleTerm>
                        </role>
                    </name>
                    <name type="personal">
                        <displayForm>Sim, Siang Meng</displayForm>
                        <namePart type="family">Sim</namePart>
                        <namePart type="given">Siang Meng</namePart>
                        <role>
                            <roleTerm type="code" authority="marcrelator">ctb</roleTerm>
                        </role>
                    </name>
                    <typeOfResource>text</typeOfResource>
                    <genre authority="dini">article</genre>
                    <originInfo>
                        <dateIssued encoding="w3cdtf" keyDate="yes">2017-06-19</dateIssued>
                    </originInfo>
                    <language>
                        <languageTerm type="code" authority="iso639-2b">eng</languageTerm>
                    </language>
                    <physicalDescription>
                        <extent unit="page">25</extent>
                    </physicalDescription>
                    <abstract lang="eng">The related-key model is now considered an important scenario for block cipher security and many schemes were broken in this model, even AES-192 and AES-256. Recently were introduced efficient computer-based search tools that can produce the best possible related-key truncated differential paths for AES. However, one has to trust the implementation of these tools and they do not provide any meaningful information on how to design a good key schedule, which remains a challenge for the community as of today. We provide in this article the first human-readable proof on the minimal number of active Sboxes in the related-key model for AES-128, without any help from a computer. More precisely, we show that any related-key differential path for AES-128 will respectively contain at least 0, 1, 3 and 9 active Sboxes for 1, 2, 3 and 4 rounds. Our proof is tight, not trivial, and actually exhibits for the first time the interplay between the key state and the internal state of an AES-like block cipher with an AES-like key schedule. As application example, we leverage our proofs to propose a new key schedule, that is not only faster (a simple permutation on the byte positions) but also ensures a higher number of active Sboxes than AES-128’s key schedule. We believe this is an important step towards a good understanding of efficient and secure key schedule designs.</abstract>
                    <subject lang="ger">
                    </subject>
                    <subject lang="eng">
First argument to forEach is not an array or JSON objectFirst argument to forEach is not an array or JSON objectFirst argument to forEach is not an array or JSON objectFirst argument to forEach is not an array or JSON object                    </subject>
                    <identifier type="doi">10.13154/tosc.v2017.i2.59-83</identifier>
                    <accessCondition type="use and reproduction" xlink:href="https://creativecommons.org/licenses/by/4.0">CC BY 4.0</accessCondition>
                    <recordInfo>
                        <recordIdentifier>rub-journals_638</recordIdentifier>
                    </recordInfo>
                    <extension>
                        <vl:doctype>oaArticle</vl:doctype>
                    </extension>
                </mods>
            </mets:xmlData>
        </mets:mdWrap>
    </mets:dmdSec>
    <mets:fileSec>
        <mets:fileGrp USE="pdf upload">
            <mets:file MIMETYPE="application/pdf" ID="FILE0_rub-journals_638">
                <mets:FLocat xlink:href="https://tosc.iacr.org/index.php/ToSC/article/download/638/606" LOCTYPE="URL"/>
            </mets:file>
        </mets:fileGrp>
        <mets:fileGrp USE="generic file">
            <mets:file MIMETYPE="application/pdf" ID="FILE1_rub-journals_638">
                <mets:FLocat xlink:href="https://tosc.iacr.org/index.php/ToSC/article/download/638/7580" LOCTYPE="URL"/>
            </mets:file>
        </mets:fileGrp>
        <mets:fileGrp USE="generic file">
            <mets:file MIMETYPE="" ID="FILE2_rub-journals_638">
                <mets:FLocat xlink:href="https://tosc.iacr.org/index.php/ToSC/article/download/638/7497" LOCTYPE="URL"/>
            </mets:file>
        </mets:fileGrp>
    </mets:fileSec>
    <mets:structMap TYPE="LOGICAL">
        <mets:div TYPE="document" ID="rub-journals_638" DMDID="DMD_rub-journals_638">
            <mets:fptr FILEID="FILE0_rub-journals_638"/>
            <mets:div TYPE="part" ID="PART1_rub-journals_638" LABEL="">
                <mets:fptr FILEID="FILE1_rub-journals_638"/>
            </mets:div>
            <mets:div TYPE="part" ID="PART2_rub-journals_638" LABEL="">
                <mets:fptr FILEID="FILE2_rub-journals_638"/>
            </mets:div>
        </mets:div>
    </mets:structMap>
</mets:mets>
