<mets:mets xmlns:mets="http://www.loc.gov/METS/" xmlns:mods="http://www.loc.gov/mods/v3" xmlns:xlink="http://www.w3.org/1999/xlink">
    <mets:dmdSec ID="DMD_rub-journals_7392">
        <mets:mdWrap MIMETYPE="text/xml" MDTYPE="MODS">
            <mets:xmlData>
                <mods xmlns="http://www.loc.gov/mods/v3" version="3.7" xmlns:vl="http://visuallibrary.net/vl">
                    <titleInfo lang="eng">
                        <title>Glitch-Resistant Masking Revisited</title>
                        <subTitle>or Why Proofs in the Robust Probing Model are Needed</subTitle>
                    </titleInfo>
                    <name type="personal">
                        <displayForm>Moos, Thorben</displayForm>
                        <namePart type="family">Moos</namePart>
                        <namePart type="given">Thorben</namePart>
                        <role>
                            <roleTerm type="code" authority="marcrelator">ctb</roleTerm>
                        </role>
                    </name>
                    <name type="personal">
                        <displayForm>Moradi, Amir</displayForm>
                        <namePart type="family">Moradi</namePart>
                        <namePart type="given">Amir</namePart>
                        <role>
                            <roleTerm type="code" authority="marcrelator">ctb</roleTerm>
                        </role>
                    </name>
                    <name type="personal">
                        <displayForm>Schneider, Tobias</displayForm>
                        <namePart type="family">Schneider</namePart>
                        <namePart type="given">Tobias</namePart>
                        <role>
                            <roleTerm type="code" authority="marcrelator">ctb</roleTerm>
                        </role>
                    </name>
                    <name type="personal">
                        <displayForm>Standaert, François-Xavier</displayForm>
                        <namePart type="family">Standaert</namePart>
                        <namePart type="given">François-Xavier</namePart>
                        <role>
                            <roleTerm type="code" authority="marcrelator">ctb</roleTerm>
                        </role>
                    </name>
                    <typeOfResource>text</typeOfResource>
                    <genre authority="dini">article</genre>
                    <originInfo>
                        <dateIssued encoding="w3cdtf" keyDate="yes">2019-02-28</dateIssued>
                    </originInfo>
                    <language>
                        <languageTerm type="code" authority="iso639-2b">eng</languageTerm>
                    </language>
                    <physicalDescription>
                        <extent unit="page">37</extent>
                    </physicalDescription>
                    <abstract lang="eng">Implementing the masking countermeasure in hardware is a delicate task. Various solutions have been proposed for this purpose over the last years: we focus on Threshold Implementations (TIs), Domain-Oriented Masking (DOM), the Unified Masking Approach (UMA) and Generic Low Latency Masking (GLM). The latter generally come with innovative ideas to cope with physical defaults such as glitches. Yet, and in contrast to the situation in software-oriented masking, these schemes have not been formally proven at arbitrary security orders and their composability properties were left unclear. So far, only a 2-cycle implementation of the seminal masking scheme by Ishai, Sahai and Wagner has been shown secure and composable in the robust probing model – a variation of the probing model aimed to capture physical defaults such as glitches – for any number of shares.In this paper, we argue that this lack of proofs for TIs, DOM, UMA and GLM makes the interpretation of their security guarantees difficult as the number of shares increases. For this purpose, we first put forward that the higher-order variants of all these schemes are affected by (local or composability) security flaws in the (robust) probing model, due to insufficient refreshing. We then show that composability and robustness against glitches cannot be analyzed independently. We finally detail how these abstract flaws translate into concrete (experimental) attacks, and discuss the additional constraints robust probing security implies on the need of registers. Despite not systematically leading to improved complexities at low security orders, e.g., with respect to the required number of measurements for a successful attack, we argue that these weaknesses provide a case for the need of security proofs in the robust probing model (or a similar abstraction) at higher security orders.</abstract>
                    <subject lang="ger">
                    </subject>
                    <subject lang="eng">
First argument to forEach is not an array or JSON objectFirst argument to forEach is not an array or JSON objectFirst argument to forEach is not an array or JSON objectFirst argument to forEach is not an array or JSON objectFirst argument to forEach is not an array or JSON objectFirst argument to forEach is not an array or JSON objectFirst argument to forEach is not an array or JSON objectFirst argument to forEach is not an array or JSON object                    </subject>
                    <identifier type="doi">10.13154/tches.v2019.i2.256-292</identifier>
                    <accessCondition type="use and reproduction" xlink:href="https://creativecommons.org/licenses/by/4.0">CC BY 4.0</accessCondition>
                    <recordInfo>
                        <recordIdentifier>rub-journals_7392</recordIdentifier>
                    </recordInfo>
                    <extension>
                        <vl:doctype>oaArticle</vl:doctype>
                    </extension>
                </mods>
            </mets:xmlData>
        </mets:mdWrap>
    </mets:dmdSec>
    <mets:fileSec>
        <mets:fileGrp USE="pdf upload">
            <mets:file MIMETYPE="application/pdf" ID="FILE0_rub-journals_7392">
                <mets:FLocat xlink:href="https://tches.iacr.org/index.php/TCHES/article/download/7392/6564" LOCTYPE="URL"/>
            </mets:file>
        </mets:fileGrp>
        <mets:fileGrp USE="generic file">
            <mets:file MIMETYPE="application/pdf" ID="FILE1_rub-journals_7392">
                <mets:FLocat xlink:href="https://tches.iacr.org/index.php/TCHES/article/download/7392/7897" LOCTYPE="URL"/>
            </mets:file>
        </mets:fileGrp>
        <mets:fileGrp USE="generic file">
            <mets:file MIMETYPE="" ID="FILE2_rub-journals_7392">
                <mets:FLocat xlink:href="https://tches.iacr.org/index.php/TCHES/article/download/7392/7898" LOCTYPE="URL"/>
            </mets:file>
        </mets:fileGrp>
    </mets:fileSec>
    <mets:structMap TYPE="LOGICAL">
        <mets:div TYPE="document" ID="rub-journals_7392" DMDID="DMD_rub-journals_7392">
            <mets:fptr FILEID="FILE0_rub-journals_7392"/>
            <mets:div TYPE="part" ID="PART1_rub-journals_7392" LABEL="">
                <mets:fptr FILEID="FILE1_rub-journals_7392"/>
            </mets:div>
            <mets:div TYPE="part" ID="PART2_rub-journals_7392" LABEL="">
                <mets:fptr FILEID="FILE2_rub-journals_7392"/>
            </mets:div>
        </mets:div>
    </mets:structMap>
</mets:mets>
