<mets:mets xmlns:mets="http://www.loc.gov/METS/" xmlns:mods="http://www.loc.gov/mods/v3" xmlns:xlink="http://www.w3.org/1999/xlink">
    <mets:dmdSec ID="DMD_rub-journals_7753">
        <mets:mdWrap MIMETYPE="text/xml" MDTYPE="MODS">
            <mets:xmlData>
                <mods xmlns="http://www.loc.gov/mods/v3" version="3.7" xmlns:vl="http://visuallibrary.net/vl">
                    <titleInfo lang="eng">
                        <title>„Der Aufstieg findet nicht statt.“ Frauen und Führungspositionen in der Gewerkschaft Öffentliche Dienste, Transport und Verkehr (ÖTV) in den 1950er und 1960er Jahren</title>
                    </titleInfo>
                    <name type="personal">
                        <displayForm>Kreutzer, Susanne</displayForm>
                        <namePart type="family">Kreutzer</namePart>
                        <namePart type="given">Susanne</namePart>
                        <role>
                            <roleTerm type="code" authority="marcrelator">ctb</roleTerm>
                        </role>
                    </name>
                    <typeOfResource>text</typeOfResource>
                    <genre authority="dini">article</genre>
                    <originInfo>
                        <dateIssued encoding="w3cdtf" keyDate="yes">2015-01-22</dateIssued>
                    </originInfo>
                    <language>
                        <languageTerm type="code" authority="iso639-2b">eng</languageTerm>
                    </language>
                    <physicalDescription>
                        <extent unit="page">11</extent>
                    </physicalDescription>
                    <abstract lang="eng">The paper exemplifies the career opportunities of women describing the German trade union ÖTV (Public service and transport) in the 1950s und 1960s. It focuses on the biographies of four women who actively participated in the union’s women’s policy and the support of female nurses. The paper shows that the time of reconstructing the union offered a chance for women even without any political experiences to take over functions in the organization. However, if the women aspired to a position outside the area of the union’s women’s policy they met the strong opposition of the male union members. It can be shown that the lack of political experience was regarded highly different between women and men. Whereas men got the support of the organization, in the case of women the reference to missing political experience was used to exclude them from influential positions.</abstract>
                    <subject lang="ger">
                    </subject>
                    <subject lang="eng">
First argument to forEach is not an array or JSON objectFirst argument to forEach is not an array or JSON objectFirst argument to forEach is not an array or JSON objectFirst argument to forEach is not an array or JSON objectFirst argument to forEach is not an array or JSON objectFirst argument to forEach is not an array or JSON objectFirst argument to forEach is not an array or JSON objectFirst argument to forEach is not an array or JSON objectFirst argument to forEach is not an array or JSON objectFirst argument to forEach is not an array or JSON object                    </subject>
                    <identifier type="doi">10.13154/mts.35.2006.167-177</identifier>
                    <recordInfo>
                        <recordIdentifier>rub-journals_7753</recordIdentifier>
                    </recordInfo>
                    <extension>
                        <vl:doctype>oaArticle</vl:doctype>
                    </extension>
                </mods>
            </mets:xmlData>
        </mets:mdWrap>
    </mets:dmdSec>
    <mets:fileSec>
        <mets:fileGrp USE="pdf upload">
            <mets:file MIMETYPE="application/pdf" ID="FILE0_rub-journals_7753">
                <mets:FLocat xlink:href="https://moving-the-social.ub.rub.de/index.php/MTS/article/download/7753/6925" LOCTYPE="URL"/>
            </mets:file>
        </mets:fileGrp>
    </mets:fileSec>
    <mets:structMap TYPE="LOGICAL">
        <mets:div TYPE="document" ID="rub-journals_7753" DMDID="DMD_rub-journals_7753">
            <mets:fptr FILEID="FILE0_rub-journals_7753"/>
        </mets:div>
    </mets:structMap>
</mets:mets>
